genf.py
genf-0.1.0.dist-info/LICENSE
genf-0.1.0.dist-info/METADATA
genf-0.1.0.dist-info/WHEEL
genf-0.1.0.dist-info/entry_points.txt
genf-0.1.0.dist-info/top_level.txt
genf-0.1.0.dist-info/RECORD
