Metadata-Version: 2.1
Name: genf
Version: 0.1.0
Summary: Extract file names and contents from a directory
Home-page: https://marhaendev.com
Author: marhaendev
Author-email: marhaendev@gmail.com
License: UNKNOWN
Platform: UNKNOWN
Classifier: Programming Language :: Python :: 3
Classifier: License :: OSI Approved :: MIT License
Classifier: Operating System :: OS Independent
Requires-Python: >=3.6
License-File: LICENSE
